fastapi_docx/__init__.py
fastapi_docx/exception_finder.py
fastapi_docx/openapi.py
fastapi_docx/py.typed
fastapi_docx/response_generator.py
fastapi_docx-1.0.3.dist-info/LICENSE
fastapi_docx-1.0.3.dist-info/METADATA
fastapi_docx-1.0.3.dist-info/WHEEL
fastapi_docx-1.0.3.dist-info/RECORD
