Metadata-Version: 2.3
Name: fastapi-docx
Version: 1.0.3
Summary: Extend a FastAPI OpenAPI spec to include all possible HTTPException or custom Exception response schemas.
Home-page: https://github.com/Saran33/fastapi-docx
License: MIT
Author: Saran Connolly
Author-email: saran@example.com
Requires-Python: >=3.10,<4.0.0
Classifier: Intended Audience :: Developers
Classifier: License :: OSI Approved :: MIT License
Classifier: Operating System :: OS Independent
Classifier: Programming Language :: Python
Classifier: Programming Language :: Python :: 3
Classifier: Programming Language :: Python :: 3.10
Classifier: Programming Language :: Python :: 3.11
Classifier: Programming Language :: Python :: 3.12
Classifier: Programming Language :: Python :: 3.13
Classifier: Programming Language :: Python :: 3 :: Only
Classifier: Topic :: Software Development :: Build Tools
Classifier: Topic :: Software Development :: Libraries :: Python Modules
Requires-Dist: fastapi (>=0.115.8,<=0.116.0)
Requires-Dist: pydantic (>=2.6.1,<3.0.0)
Project-URL: Repository, https://github.com/Saran33/fastapi-docx
